xchem_chimp/__init__.py
xchem_chimp/__main__.py
xchem_chimp/_version.py
xchem_chimp/version.py
xchem_chimp/base/__init__.py
xchem_chimp/base/chimp_base.py
xchem_chimp/base/chimp_errors.py
xchem_chimp/base/chimp_utils.py
xchem_chimp/detector/__init__.py
xchem_chimp/detector/chimp_detector.py
xchem_chimp/detector/coord_generator.py
xchem_chimp/detector/detector_config.py
xchem_chimp/detector/detector_dataset.py
xchem_chimp/detector/detector_utils.py
xchem_chimp/detector/mask_saver.py
xchem_chimp/detector/background_images/d1_background.png
xchem_chimp/detector/background_images/d2_background.png
xchem_chimp/detector/background_images/d3_background.png
xchem_chimp-1.0.1.dist-info/LICENSE
xchem_chimp-1.0.1.dist-info/METADATA
xchem_chimp-1.0.1.dist-info/WHEEL
xchem_chimp-1.0.1.dist-info/entry_points.txt
xchem_chimp-1.0.1.dist-info/top_level.txt
xchem_chimp-1.0.1.dist-info/RECORD
