Metadata-Version: 2.1
Name: xchem-chimp
Version: 1.0.1
Summary: XChem CHIMP
Author-email: Olly King <olly.king@diamond.ac.uk>
License: Apache License
Project-URL: GitLab, https://gitlab.diamond.ac.uk/data-analysis/imaging/xchem-chimp
Classifier: Development Status :: 3 - Alpha
Classifier: License :: OSI Approved :: Apache Software License
Classifier: Programming Language :: Python :: 3.9
Classifier: Programming Language :: Python :: 3.10
Classifier: Programming Language :: Python :: 3.11
Requires-Python: >=3.9
License-File: LICENSE
Requires-Dist: imageio
Requires-Dist: matplotlib
Requires-Dist: scikit-image
Requires-Dist: torch
Requires-Dist: torchvision
Requires-Dist: albumentations
Requires-Dist: requests
Provides-Extra: dev
Requires-Dist: black (==22.12.0) ; extra == 'dev'
Requires-Dist: mypy ; extra == 'dev'
Requires-Dist: flake8-isort ; extra == 'dev'
Requires-Dist: Flake8-pyproject ; extra == 'dev'
Requires-Dist: pipdeptree ; extra == 'dev'
Requires-Dist: pre-commit ; extra == 'dev'
Requires-Dist: pytest-cov ; extra == 'dev'
Requires-Dist: pydocstyle[toml] ; extra == 'dev'
Requires-Dist: tox-direct ; extra == 'dev'
Requires-Dist: types-mock ; extra == 'dev'
Requires-Dist: types-PyYAML ; extra == 'dev'
Provides-Extra: docs
Requires-Dist: pydata-sphinx-theme (>=0.12) ; extra == 'docs'
Requires-Dist: sphinx-argparse ; extra == 'docs'
Requires-Dist: sphinx-autobuild ; extra == 'docs'
Requires-Dist: sphinx-copybutton ; extra == 'docs'
Requires-Dist: sphinx-design ; extra == 'docs'
Requires-Dist: tox-direct ; extra == 'docs'
Requires-Dist: nbsphinx ; extra == 'docs'
Requires-Dist: pandoc ; extra == 'docs'
Requires-Dist: ipykernel ; extra == 'docs'
Requires-Dist: h5py ; extra == 'docs'
Requires-Dist: matplotlib ; extra == 'docs'
